LICENSE
autolinkedin/__main__.py
autolinkedin/base_linkedin.py
autolinkedin/crons/__init__.py
autolinkedin/crons/cron_jobs.py
autolinkedin/decorators.py
autolinkedin/exceptions.py
autolinkedin/linkedin.py
autolinkedin/ln_settings.py
autolinkedin/log_config/log_config.yaml
autolinkedin/read_envs.py
autolinkedin/scripts/__init__.py
autolinkedin/scripts/sample_script.py
autolinkedin/settings.py
autolinkedin/utils/core.py
autolinkedin/wait.py
autolinkedin-1.6.4.dist-info/LICENSE
autolinkedin-1.6.4.dist-info/METADATA
autolinkedin-1.6.4.dist-info/WHEEL
autolinkedin-1.6.4.dist-info/RECORD
