Metadata-Version: 2.1
Name: autolinkedin
Version: 1.6.4
Summary: Python package to automate activities on LinkedIn.
Home-page: https://github.com/inquilabee/LinkedinPy
License: MIT
Keywords: linkedin,autolinkedin,selenium,linkedin automation
Author: Vishal Kumar Mishra
Author-email: vishal.k.mishra2@gmail.com
Requires-Python: >=3.10,<4.0
Classifier: License :: OSI Approved :: MIT License
Classifier: Programming Language :: Python :: 3
Classifier: Programming Language :: Python :: 3.10
Classifier: Programming Language :: Python :: 3.11
Requires-Dist: PyYAML (>=6.0.1,<7.0.0)
Requires-Dist: django-environ (>=0.11.1,<0.12.0)
Requires-Dist: python-crontab (>=3.0.0,<4.0.0)
Requires-Dist: python-dotenv (>=1.0.0,<2.0.0)
Requires-Dist: selenium (>=4.12.0,<5.0.0)
Requires-Dist: seleniumtabs (>=0.5.6,<0.6.0)
Project-URL: Repository, https://github.com/inquilabee/LinkedinPy
